setup.py
adb_logger/Logcat.py
adb_logger/Ping.py
adb_logger/Terminal.py
adb_logger/__init__.py
adb_logger/adb_logger.py
adb_logger.egg-info/PKG-INFO
adb_logger.egg-info/SOURCES.txt
adb_logger.egg-info/dependency_links.txt
adb_logger.egg-info/not-zip-safe
adb_logger.egg-info/top_level.txt